[
  {"sym":"PERSISTENT.NS","name":"Persistent Systems","sector":"IT"},
  {"sym":"COFORGE.NS","name":"Coforge","sector":"IT"},
  {"sym":"MPHASIS.NS","name":"Mphasis","sector":"IT"},
  {"sym":"KPITTECH.NS","name":"KPIT Technologies","sector":"IT"},
  {"sym":"LTTS.NS","name":"L&T Technology Services","sector":"IT"},
  {"sym":"TATAELXSI.NS","name":"Tata Elxsi","sector":"IT"},
  {"sym":"AUROPHARMA.NS","name":"Aurobindo Pharma","sector":"Pharma"},
  {"sym":"TORNTPHARM.NS","name":"Torrent Pharmaceuticals","sector":"Pharma"},
  {"sym":"ALKEM.NS","name":"Alkem Laboratories","sector":"Pharma"},
  {"sym":"LAURUSLABS.NS","name":"Laurus Labs","sector":"Pharma"},
  {"sym":"GLENMARK.NS","name":"Glenmark Pharma","sector":"Pharma"},
  {"sym":"ZYDUSLIFE.NS","name":"Zydus Lifesciences","sector":"Pharma"},
  {"sym":"PIIND.NS","name":"PI Industries","sector":"Agrochemicals"},
  {"sym":"DEEPAKNTR.NS","name":"Deepak Nitrite","sector":"Chemicals"},
  {"sym":"NAVINFLUOR.NS","name":"Navin Fluorine","sector":"Chemicals"},
  {"sym":"ATUL.NS","name":"Atul Ltd","sector":"Chemicals"},
  {"sym":"CHOLAFIN.NS","name":"Cholamandalam Finance","sector":"Finance"},
  {"sym":"ABCAPITAL.NS","name":"Aditya Birla Capital","sector":"Finance"},
  {"sym":"MFSL.NS","name":"Max Financial Services","sector":"Insurance"},
  {"sym":"KFINTECH.NS","name":"KFin Technologies","sector":"Finance"},
  {"sym":"CANBK.NS","name":"Canara Bank","sector":"Banking"},
  {"sym":"BANKBARODA.NS","name":"Bank of Baroda","sector":"Banking"},
  {"sym":"FEDERALBNK.NS","name":"Federal Bank","sector":"Banking"},
  {"sym":"IDFCFIRSTB.NS","name":"IDFC First Bank","sector":"Banking"},
  {"sym":"RBLBANK.NS","name":"RBL Bank","sector":"Banking"},
  {"sym":"VOLTAS.NS","name":"Voltas","sector":"Consumer Durables"},
  {"sym":"HAVELLS.NS","name":"Havells India","sector":"Consumer Durables"},
  {"sym":"POLYCAB.NS","name":"Polycab India","sector":"Consumer Durables"},
  {"sym":"DIXON.NS","name":"Dixon Technologies","sector":"Electronics"},
  {"sym":"AMBER.NS","name":"Amber Enterprises","sector":"Electronics"},
  {"sym":"KAYNES.NS","name":"Kaynes Technology","sector":"Electronics"},
  {"sym":"ASTRAL.NS","name":"Astral Ltd","sector":"Building Materials"},
  {"sym":"KAJARIACER.NS","name":"Kajaria Ceramics","sector":"Building Materials"},
  {"sym":"PAGEIND.NS","name":"Page Industries","sector":"Textiles"},
  {"sym":"LALPATHLAB.NS","name":"Dr Lal PathLabs","sector":"Healthcare"},
  {"sym":"METROPOLIS.NS","name":"Metropolis Healthcare","sector":"Healthcare"},
  {"sym":"MAXHEALTH.NS","name":"Max Healthcare","sector":"Healthcare"},
  {"sym":"IRCTC.NS","name":"IRCTC","sector":"Travel"},
  {"sym":"NAUKRI.NS","name":"Info Edge (Naukri)","sector":"Internet"},
  {"sym":"GODREJPROP.NS","name":"Godrej Properties","sector":"Real Estate"},
  {"sym":"OBEROIRLTY.NS","name":"Oberoi Realty","sector":"Real Estate"},
  {"sym":"PRESTIGE.NS","name":"Prestige Estates","sector":"Real Estate"},
  {"sym":"PHOENIXLTD.NS","name":"Phoenix Mills","sector":"Real Estate"},
  {"sym":"SOLARINDS.NS","name":"Solar Industries","sector":"Defence"},
  {"sym":"AARTIIND.NS","name":"Aarti Industries","sector":"Chemicals"},
  {"sym":"MOTHERSON.NS","name":"Motherson Sumi Systems","sector":"Auto Ancillary"},
  {"sym":"TIINDIA.NS","name":"Tube Investments","sector":"Auto Ancillary"},
  {"sym":"SCHAEFFLER.NS","name":"Schaeffler India","sector":"Auto Ancillary"},
  {"sym":"SUNDRMFAST.NS","name":"Sundram Fasteners","sector":"Auto Ancillary"}
]
